Workbook

Sheet Mode d'emploi
A1: Budget Facile 💸
A2: Ton tableau de budget automatique — 10 minutes par semaine
A4: Comment ça marche ?
A5: 1. Onglet « Budget du mois » : entre tes revenus et ton budget prévu par catégorie.
A6: 2. Onglet « Dépenses » : note chaque dépense (date, description, catégorie, montant).
A7: 3. Tout le reste se calcule tout seul : total dépensé, reste à vivre, graphique.
A8: 4. Onglet « Dettes » : vois combien de mois il te reste avant d'être libre.
A9: 5. Onglet « Défi 52 semaines » : coche chaque semaine, regarde ton épargne grandir.
A11: Légende
A12: Cellules jaunes = à remplir par toi. Cellules blanches = calcul automatique (ne pas toucher).
A13: Les lignes déjà remplies sont des exemples : remplace-les par tes propres chiffres.
A15: Exemple | B15: ← cellule à remplir

Sheet Budget du mois
A1: Mon budget du mois
A2: Remplis les cases jaunes, tout le reste est automatique
A4: Revenus
A5: Source | B5: Montant (€)
A6: Salaire | B6: 1850
A7: Aides / allocations | B7: 0
A8: Revenus complémentaires | B8: 120
A9: Total revenus | B9: =SUM(B6:B8) -> 1970
A11: Dépenses par catégorie
A12: Catégorie | B12: Prévu (€) | C12: Réel (€) | D12: Reste (€) | E12: % utilisé
A13: Logement | B13: 700 | C13: =SUMIFS(Dépenses!$D$5:$D$204,Dépenses!$C$5:$C$204,A13) -> 650 | D13: =B13-C13 -> 50 | E13: =IF(B13=0,0,C13/B13) -> 0.92857143
A14: Courses | B14: 300 | C14: =SUMIFS(Dépenses!$D$5:$D$204,Dépenses!$C$5:$C$204,A14) -> 174.1 | D14: =B14-C14 -> 125.9 | E14: =IF(B14=0,0,C14/B14) -> 0.58033333
A15: Transport | B15: 140 | C15: =SUMIFS(Dépenses!$D$5:$D$204,Dépenses!$C$5:$C$204,A15) -> 131.4 | D15: =B15-C15 -> 8.6 | E15: =IF(B15=0,0,C15/B15) -> 0.93857143
A16: Abonnements | B16: 45 | C16: =SUMIFS(Dépenses!$D$5:$D$204,Dépenses!$C$5:$C$204,A16) -> 44.47 | D16: =B16-C16 -> 0.53 | E16: =IF(B16=0,0,C16/B16) -> 0.98822222
A17: Sorties & loisirs | B17: 100 | C17: =SUMIFS(Dépenses!$D$5:$D$204,Dépenses!$C$5:$C$204,A17) -> 46.5 | D17: =B17-C17 -> 53.5 | E17: =IF(B17=0,0,C17/B17) -> 0.465
A18: Shopping | B18: 80 | C18: =SUMIFS(Dépenses!$D$5:$D$204,Dépenses!$C$5:$C$204,A18) -> 79.99 | D18: =B18-C18 -> 0.01 | E18: =IF(B18=0,0,C18/B18) -> 0.999875
A19: Santé | B19: 30 | C19: =SUMIFS(Dépenses!$D$5:$D$204,Dépenses!$C$5:$C$204,A19) -> 12.8 | D19: =B19-C19 -> 17.2 | E19: =IF(B19=0,0,C19/B19) -> 0.42666667
A20: Épargne | B20: 150 | C20: =SUMIFS(Dépenses!$D$5:$D$204,Dépenses!$C$5:$C$204,A20) -> 150 | D20: =B20-C20 -> 0 | E20: =IF(B20=0,0,C20/B20) -> 1
A21: Autre | B21: 50 | C21: =SUMIFS(Dépenses!$D$5:$D$204,Dépenses!$C$5:$C$204,A21) -> 0 | D21: =B21-C21 -> 50 | E21: =IF(B21=0,0,C21/B21) -> 0
A22: Total | B22: =SUM(B13:B21) -> 1595 | C22: =SUM(C13:C21) -> 1289.26 | D22: =SUM(D13:D21) -> 305.74 | E22: =IF(B22=0,0,C22/B22) -> 0.80831348
A24: Résumé
A25: Total revenus | B25: =B9 -> 1970
A26: Total dépensé | B26: =C22 -> 1289.26
A27: 💰 Reste à vivre | B27: =B9-C22 -> 680.74
A28: Taux d'épargne | B28: =IF(B9=0,0,C20/B9) -> 0.076142132

Sheet Dépenses
A1: Journal des dépenses
A2: Note chaque dépense ici — la catégorie se choisit dans une liste
A4: Date | B4: Description | C4: Catégorie | D4: Montant (€)
A5: 46296 | B5: Loyer | C5: Logement | D5: 650
A6: 46297 | B6: Supermarché | C6: Courses | D6: 82.4
A7: 46298 | B7: Pass Navigo | C7: Transport | D7: 86.4
A8: 46299 | B8: Netflix | C8: Abonnements | D8: 13.49
A9: 46300 | B9: Spotify | C9: Abonnements | D9: 10.99
A10: 46301 | B10: Resto avec amis | C10: Sorties & loisirs | D10: 34
A11: 46303 | B11: Marché | C11: Courses | D11: 27.5
A12: 46304 | B12: Pharmacie | C12: Santé | D12: 12.8
A13: 46306 | B13: Baskets | C13: Shopping | D13: 79.99
A14: 46307 | B14: Virement épargne | C14: Épargne | D14: 150
A15: 46309 | B15: Supermarché | C15: Courses | D15: 64.2
A16: 46310 | B16: Essence | C16: Transport | D16: 45
... A18: 46315 | B18: Forfait mobile | C18: Abonnements | D18: 19.99

Sheet Dettes
A1: Plan anti-dettes
A2: Vois en combien de mois tu seras libéré(e)
A4: Crédit | B4: Reste à payer (€) | C4: Taux annuel | D4: Mensualité (€) | E4: Mois restants | F4: Intérêts estimés (€)
A5: Crédit auto | B5: 4200 | C5: 0.049 | D5: 180 | E5: =IF(OR(B5="",B5=0),"",IF(C5=0,ROUNDUP(B5/D5,0),IF(D5<=B5*C5/12,"Mensualité trop faible",ROUNDUP(NPER(C5/12,-D5,B5),0)))) -> 25 | F5: =IF(ISNUMBER(E5),MAX(0,E5*D5-B5),"") -> 300
A6: Carte de crédit | B6: 950 | C6: 0.19 | D6: 80 | E6: =IF(OR(B6="",B6=0),"",IF(C6=0,ROUNDUP(B6/D6,0),IF(D6<=B6*C6/12,"Mensualité trop faible",ROUNDUP(NPER(C6/12,-D6,B6),0)))) -> 14 | F6: =IF(ISNUMBER(E6),MAX(0,E6*D6-B6),"") -> 170
A7: Prêt étudiant | B7: 3000 | C7: 0.012 | D7: 100 | E7: =IF(OR(B7="",B7=0),"",IF(C7=0,ROUNDUP(B7/D7,0),IF(D7<=B7*C7/12,"Mensualité trop faible",ROUNDUP(NPER(C7/12,-D7,B7),0)))) -> 31 | F7: =IF(ISNUMBER(E7),MAX(0,E7*D7-B7),"") -> 100
E8: =IF(OR(B8="",B8=0),"",IF(C8=0,ROUNDUP(B8/D8,0),IF(D8<=B8*C8/12,"Mensualité trop faible",ROUNDUP(NPER(C8/12,-D8,B8),0)))) | F8: =IF(ISNUMBER(E8),MAX(0,E8*D8-B8),"")
E9: =IF(OR(B9="",B9=0),"",IF(C9=0,ROUNDUP(B9/D9,0),IF(D9<=B9*C9/12,"Mensualité trop faible",ROUNDUP(NPER(C9/12,-D9,B9),0)))) | F9: =IF(ISNUMBER(E9),MAX(0,E9*D9-B9),"")
E10: =IF(OR(B10="",B10=0),"",IF(C10=0,ROUNDUP(B10/D10,0),IF(D10<=B10*C10/12,"Mensualité trop faible",ROUNDUP(NPER(C10/12,-D10,B10),0)))) | F10: =IF(ISNUMBER(E10),MAX(0,E10*D10-B10),"")
E11: =IF(OR(B11="",B11=0),"",IF(C11=0,ROUNDUP(B11/D11,0),IF(D11<=B11*C11/12,"Mensualité trop faible",ROUNDUP(NPER(C11/12,-D11,B11),0)))) | F11: =IF(ISNUMBER(E11),MAX(0,E11*D11-B11),"")
E12: =IF(OR(B12="",B12=0),"",IF(C12=0,ROUNDUP(B12/D12,0),IF(D12<=B12*C12/12,"Mensualité trop faible",ROUNDUP(NPER(C12/12,-D12,B12),0)))) | F12: =IF(ISNUMBER(E12),MAX(0,E12*D12-B12),"")
A14: Total | B14: =SUM(B5:B12) -> 8150 | D14: =SUM(D5:D12) -> 360 | E14: =IF(COUNT(E5:E12)=0,"",MAX(E5:E12)) -> 31 | F14: =SUM(F5:F12) -> 570
A16: 🎉 Libre de toute dette dans : | C16: =IF(E14="","-",E14&" mois") -> 31 mois
A17: Astuce : rembourse d'abord le crédit au taux le plus élevé (méthode « avalanche »).

Sheet Défi 52 semaines
A1: Défi épargne 52 semaines
A2: Semaine 1 : 1 €, semaine 2 : 2 €… jusqu'à 52 €. Mets « x » quand c'est fait !
A4: Semaine | B4: À épargner (€) | C4: Fait ? (x) | D4: Cumul épargné (€)
A5: 1 | B5: =A5*$G$5 -> 1 | C5: x | D5: =SUMIFS($B$5:B5,$C$5:C5,"x") -> 1 | F5: Montant de base (€) | G5: 1
A6: 2 | B6: =A6*$G$5 -> 2 | C6: x | D6: =SUMIFS($B$5:B6,$C$5:C6,"x") -> 3
A7: 3 | B7: =A7*$G$5 -> 3 | C7: x | D7: =SUMIFS($B$5:B7,$C$5:C7,"x") -> 6 | F7: Objectif total | G7: =SUM(B5:B56) -> 1378
A8: 4 | B8: =A8*$G$5 -> 4 | C8: x | D8: =SUMIFS($B$5:B8,$C$5:C8,"x") -> 10 | F8: Déjà épargné | G8: =SUMIFS(B5:B56,C5:C56,"x") -> 21
A9: 5 | B9: =A9*$G$5 -> 5 | C9: x | D9: =SUMIFS($B$5:B9,$C$5:C9,"x") -> 15 | F9: Progression | G9: =IF(G7=0,0,G8/G7) -> 0.015239478
A10: 6 | B10: =A10*$G$5 -> 6 | C10: x | D10: =SUMIFS($B$5:B10,$C$5:C10,"x") -> 21
A11: 7 | B11: =A11*$G$5 -> 7 | D11: =SUMIFS($B$5:B11,$C$5:C11,"x") -> 21 | F11: Change le montant de base (ex. 2 €) pour doubler ton objectif.
A12: 8 | B12: =A12*$G$5 -> 8 | D12: =SUMIFS($B$5:B12,$C$5:C12,"x") -> 21
A13: 9 | B13: =A13*$G$5 -> 9 | D13: =SUMIFS($B$5:B13,$C$5:C13,"x") -> 21
A14: 10 | B14: =A14*$G$5 -> 10 | D14: =SUMIFS($B$5:B14,$C$5:C14,"x") -> 21
A15: 11 | B15: =A15*$G$5 -> 11 | D15: =SUMIFS($B$5:B15,$C$5:C15,"x") -> 21
A16: 12 | B16: =A16*$G$5 -> 12 | D16: =SUMIFS($B$5:B16,$C$5:C16,"x") -> 21
A17: 13 | B17: =A17*$G$5 -> 13 | D17: =SUMIFS($B$5:B17,$C$5:C17,"x") -> 21
A18: 14 | B18: =A18*$G$5 -> 14 | D18: =SUMIFS($B$5:B18,$C$5:C18,"x") -> 21
A19: 15 | B19: =A19*$G$5 -> 15 | D19: =SUMIFS($B$5:B19,$C$5:C19,"x") -> 21
A20: 16 | B20: =A20*$G$5 -> 16 | D20: =SUMIFS($B$5:B20,$C$5:C20,"x") -> 21
A21: 17 | B21: =A21*$G$5 -> 17 | D21: =SUMIFS($B$5:B21,$C$5:C21,"x") -> 21
A22: 18 | B22: =A22*$G$5 -> 18 | D22: =SUMIFS($B$5:B22,$C$5:C22,"x") -> 21
A23: 19 | B23: =A23*$G$5 -> 19 | D23: =SUMIFS($B$5:B23,$C$5:C23,"x") -> 21
... A56: 52 | B56: =A56*$G$5 -> 52 | D56: =SUMIFS($B$5:B56,$C$5:C56,"x") -> 21
